checkdeps/__init__.py
checkdeps/__main__.py
checkdeps/cli.py
checkdeps/distinfo.py
checkdeps/distinfo_inference.py
checkdeps/import_parser.py
checkdeps/metadata.py
checkdeps/py.typed
checkdeps/requirements.py
checkdeps/tests/__init__.py
checkdeps/tests/__main__.py
checkdeps/tests/cli.py
checkdeps/tests/distinfo.py
checkdeps/tests/distinfo_inference.py
checkdeps/tests/import_parser.py
checkdeps/tests/metadata.py
checkdeps-0.9.0.dist-info/LICENSE
checkdeps-0.9.0.dist-info/METADATA
checkdeps-0.9.0.dist-info/WHEEL
checkdeps-0.9.0.dist-info/top_level.txt
checkdeps-0.9.0.dist-info/RECORD
