Metadata-Version: 2.1
Name: checkdeps
Version: 0.9.0
Summary: Ensures your first-order deps are correct
Home-page: https://github.com/python-packaging/checkdeps/
Author: Tim Hatch
Author-email: tim@timhatch.com
License: MIT
Requires-Python: >=3.10
License-File: LICENSE
Requires-Dist: click >=7.0
Requires-Dist: packaging >=21.0
Requires-Dist: stdlibs >=2022.3.16
Requires-Dist: trailrunner >=1.0
Requires-Dist: toml ; python_version < "3.11"
Provides-Extra: dev
Requires-Dist: black ==23.12.1 ; extra == 'dev'
Requires-Dist: flake8 ==7.0.0 ; extra == 'dev'
Requires-Dist: mypy ==1.8.0 ; extra == 'dev'
Requires-Dist: tox ==4.12.1 ; extra == 'dev'
Requires-Dist: twine ==4.0.2 ; extra == 'dev'
Requires-Dist: ufmt ==2.3.0 ; extra == 'dev'
Requires-Dist: usort ==1.0.7 ; extra == 'dev'
Requires-Dist: wheel ==0.42.0 ; extra == 'dev'
Provides-Extra: test
Requires-Dist: coverage >=6 ; extra == 'test'
